py_danil_server-0.0.3.data/scripts/server_run
server/__init__.py
server/add_user.py
server/decorators.py
server/descriptors.py
server/metaclasses.py
server/remove_user.py
server/server.ini
server/server.py
server/server_database.py
server/server_gui.py
server/server_run
server/common/__init__.py
server/common/utils.py
server/common/variables.py
server/log/__init__.py
server/log/client_log_config.py
server/log/server_log_config.py
py_danil_server-0.0.3.dist-info/METADATA
py_danil_server-0.0.3.dist-info/WHEEL
py_danil_server-0.0.3.dist-info/top_level.txt
py_danil_server-0.0.3.dist-info/RECORD
