Metadata-Version: 2.1
Name: py-danil-server
Version: 0.0.3
Summary: Server app
Home-page: UNKNOWN
Author: Danil Mosin
Author-email: vinniopo@mail.ru
License: UNKNOWN
Platform: UNKNOWN
Requires-Dist: PyQt5
Requires-Dist: sqlalchemy
Requires-Dist: pycryptodome
Requires-Dist: pycryptodomex
